medula_cli.py
medula_cli-1.0.2.dist-info/METADATA
medula_cli-1.0.2.dist-info/WHEEL
medula_cli-1.0.2.dist-info/entry_points.txt
medula_cli-1.0.2.dist-info/top_level.txt
medula_cli-1.0.2.dist-info/RECORD
