Metadata-Version: 2.4
Name: medula-cli
Version: 1.0.2
Summary: Command-line interface for Medula AI Agent Platform
Home-page: https://github.com/Subomi-olagoke/studious-rotary-phone
Author: Medula Team
Author-email: support@medula.ai
Project-URL: Documentation, https://docs.medula.ai/cli
Project-URL: Source, https://github.com/Subomi-olagoke/studious-rotary-phone
Project-URL: Bug Reports, https://github.com/Subomi-olagoke/studious-rotary-phone/issues
Keywords: ai,cli,agent,medula,chatbot,automation
Classifier: Development Status :: 4 - Beta
Classifier: Intended Audience :: Developers
Classifier: License :: OSI Approved :: MIT License
Classifier: Programming Language :: Python :: 3
Classifier: Programming Language :: Python :: 3.8
Classifier: Programming Language :: Python :: 3.9
Classifier: Programming Language :: Python :: 3.10
Classifier: Programming Language :: Python :: 3.11
Requires-Python: >=3.8
Requires-Dist: click>=8.0.0
Requires-Dist: rich>=13.0.0
Requires-Dist: httpx>=0.24.0
Requires-Dist: keyring>=24.0.0
Dynamic: author
Dynamic: author-email
Dynamic: classifier
Dynamic: description
Dynamic: description-content-type
Dynamic: home-page
Dynamic: keywords
Dynamic: project-url
Dynamic: requires-dist
Dynamic: requires-python
Dynamic: summary
